xfil.py
xfil-0.1.2.dist-info/LICENSE
xfil-0.1.2.dist-info/METADATA
xfil-0.1.2.dist-info/WHEEL
xfil-0.1.2.dist-info/entry_points.txt
xfil-0.1.2.dist-info/top_level.txt
xfil-0.1.2.dist-info/RECORD
