Metadata-Version: 2.1
Name: xfil
Version: 0.1.2
Summary: xfil is a tool that performs blind XPath exploitation and data exfiltration. This tool is created for penetration testers performing authorized security assessments.
Home-page: https://github.com/sdcampbell/xfil
Author: Steve Campbell
Author-email: sdcampbell68@live.com
Classifier: Programming Language :: Python :: 3
Classifier: License :: OSI Approved :: Apache Software License
Classifier: Operating System :: OS Independent
Requires-Python: >=3.11
License-File: LICENSE
Requires-Dist: requests >=2.32.3
